noti/__init__.py
noti/__main__.py
noti/auth.py
noti/config.py
noti/pypi.py
noti/slack.py
noti2-1.0.5.dist-info/LICENSE
noti2-1.0.5.dist-info/METADATA
noti2-1.0.5.dist-info/WHEEL
noti2-1.0.5.dist-info/entry_points.txt
noti2-1.0.5.dist-info/RECORD
